setup.py
cfn/__init__.py
cfn.egg-info/PKG-INFO
cfn.egg-info/SOURCES.txt
cfn.egg-info/dependency_links.txt
cfn.egg-info/entry_points.txt
cfn.egg-info/requires.txt
cfn.egg-info/top_level.txt