Metadata-Version: 1.1
Name: cfn
Version: 0.0.5
Summary: Small script to manipulate AWS CloudFormation stacks
Home-page: https://github.com/hagbarddenstore/cfn
Author: Kim Johansson
Author-email: hagbarddenstore@gmail.com
License: MIT
Keywords: aws cfn cloudformation
Platform: UNKNOWN
Classifier: Development Status :: 3 - Alpha
Classifier: Intended Audience :: Developers
Classifier: License :: OSI Approved :: MIT License
Classifier: Programming Language :: Python :: 2.7
